<?xml version="1.0"?>
<Objects>
  <Object name="Object10">
    <AbsoluteLocation value="1.080212 23.315559"/>
    <Properties>
      <Property name="Angle" value="-90.3712"/>
      <Property name="Filename" value="/Objects/pipe_straight_short.hs"/>
    </Properties>
  </Object>
  <Object name="Ducky2">
    <AbsoluteLocation value="1.056911 7.533886"/>
    <Properties>
      <Property name="Angle" value="0"/>
      <Property name="Filename" value="/Objects/star_steam_allie.hs"/>
      <Property name="StarType" value="allie"/>
      <Property name="Type" value="star"/>
    </Properties>
  </Object>
  <Object name="Spout3">
    <AbsoluteLocation value="0.800001 20.000000"/>
    <Properties>
      <Property name="Angle" value="-180.77"/>
      <Property name="ConnectedSpout0" value="SWAMPY_SPOUT"/>
      <Property name="ConnectedSpoutProbability0" value="1"/>
      <Property name="Filename" value="/Objects/broken_pipe_allie.hs"/>
      <Property name="Type" value="spout"/>
    </Properties>
  </Object>
  <Object name="Fan4">
    <AbsoluteLocation value="-17.625002 -39.281250"/>
    <Properties>
      <Property name="Angle" value="7.4627"/>
      <Property name="Filename" value="/Objects/fan_24x8.hs"/>
      <Property name="Type" value="fan"/>
    </Properties>
  </Object>
  <Object name="Fan5">
    <AbsoluteLocation value="18.343750 -38.500000"/>
    <Properties>
      <Property name="Angle" value="-5.05655"/>
      <Property name="Filename" value="/Objects/fan_24x8.hs"/>
      <Property name="Type" value="fan"/>
    </Properties>
  </Object>
  <Object name="Switch6">
    <AbsoluteLocation value="0.375000 -41.390625"/>
    <Properties>
      <Property name="Angle" value="0"/>
      <Property name="ConnectedObject0" value="Fan4"/>
      <Property name="ConnectedObject1" value="Fan5"/>
      <Property name="Filename" value="/Objects/switch.hs"/>
      <Property name="Type" value="switch"/>
    </Properties>
  </Object>
  <Object name="Ducky7">
    <AbsoluteLocation value="12.156250 -6.343750"/>
    <Properties>
      <Property name="Angle" value="0"/>
      <Property name="Filename" value="/Objects/star_steam_allie.hs"/>
      <Property name="StarType" value="allie"/>
      <Property name="Type" value="star"/>
    </Properties>
  </Object>
  <Object name="Ducky8">
    <AbsoluteLocation value="-10.750002 -6.218750"/>
    <Properties>
      <Property name="Angle" value="0"/>
      <Property name="Filename" value="/Objects/star_steam_allie.hs"/>
      <Property name="StarType" value="allie"/>
      <Property name="Type" value="star"/>
    </Properties>
  </Object>
  <Object name="Object12">
    <AbsoluteLocation value="0.411911 25.293139"/>
    <Properties>
      <Property name="Angle" value="0"/>
      <Property name="Filename" value="/Objects/pipe_elbow_1.hs"/>
    </Properties>
  </Object>
  <Object name="Object15">
    <AbsoluteLocation value="-2.416840 25.983442"/>
    <Properties>
      <Property name="Angle" value="0.601469"/>
      <Property name="Filename" value="/Objects/pipe_straight_short.hs"/>
    </Properties>
  </Object>
  <Object name="Object11">
    <AbsoluteLocation value="-5.348145 26.035875"/>
    <Properties>
      <Property name="Angle" value="175.268"/>
      <Property name="Filename" value="/Objects/pipe_connector_end.hs"/>
    </Properties>
  </Object>
  <Room>
    <AbsoluteLocation value="-19.599998 27.599998"/>
  </Room>
</Objects>
