<?xml version="1.0"?>
<Objects>
  <Object name="Obj9">
    <AbsoluteLocation value="6.497474 -14.868477"/>
    <Properties>
      <Property name="Angle" value="35.7063"/>
      <Property name="Filename" value="/Objects/pipe_straight.hs"/>
    </Properties>
  </Object>
  <Object name="Obj8">
    <AbsoluteLocation value="4.007419 -20.932098"/>
    <Properties>
      <Property name="Angle" value="120.386"/>
      <Property name="Filename" value="/Objects/pipe_straight.hs"/>
    </Properties>
  </Object>
  <Object name="Spout2">
    <AbsoluteLocation value="8.918259 -12.972122"/>
    <Properties>
      <Property name="Angle" value="-53.9553"/>
      <Property name="ConnectedSpout0" value="SWAMPY_SPOUT"/>
      <Property name="ConnectedSpoutProbability0" value="1"/>
      <Property name="Filename" value="/Objects/broken_pipe.hs"/>
      <Property name="Type" value="spout"/>
    </Properties>
  </Object>
  <Object name="Star3">
    <AbsoluteLocation value="26.209843 -11.918344"/>
    <Properties>
      <Property name="Angle" value="0"/>
      <Property name="Filename" value="/Objects/star.hs"/>
      <Property name="Type" value="star"/>
    </Properties>
  </Object>
  <Object name="Star4">
    <AbsoluteLocation value="-14.397942 -19.233847"/>
    <Properties>
      <Property name="Angle" value="0"/>
      <Property name="Filename" value="/Objects/star.hs"/>
      <Property name="Type" value="star"/>
    </Properties>
  </Object>
  <Object name="Star5">
    <AbsoluteLocation value="26.629776 27.680090"/>
    <Properties>
      <Property name="Angle" value="0"/>
      <Property name="Filename" value="/Objects/star.hs"/>
      <Property name="Type" value="star"/>
    </Properties>
  </Object>
  <Object name="Obj7">
    <AbsoluteLocation value="3.693092 -17.844212"/>
    <Properties>
      <Property name="Angle" value="-63.8176"/>
      <Property name="Filename" value="/Objects/pipe_connector_90.hs"/>
    </Properties>
  </Object>
  <Object name="Obj9">
    <AbsoluteLocation value="5.282823 -22.770992"/>
    <Properties>
      <Property name="Angle" value="-53.8561"/>
      <Property name="Filename" value="/Objects/pipe_connector_end.hs"/>
    </Properties>
  </Object>
  <Object name="Obj9">
    <AbsoluteLocation value="25.250746 36.212582"/>
    <Properties>
      <Property name="Angle" value="0"/>
      <Property name="Filename" value="/Objects/icicle_large.hs"/>
      <Property name="Type" value="icyhot"/>
    </Properties>
  </Object>
  <Object name="Ducky12">
    <AbsoluteLocation value="10.562500 3.218750"/>
    <Properties>
      <Property name="Angle" value="0"/>
      <Property name="CutsRock" value="1"/>
      <Property name="Filename" value="/Objects/star_teleport.hs"/>
      <Property name="StarType" value="teleport"/>
      <Property name="TeleportMoveEase" value="both"/>
      <Property name="TeleportMoveTime" value="2"/>
      <Property name="TeleportWaitTime" value="2"/>
      <Property name="Type" value="star"/>
    </Properties>
  </Object>
  <Object name="Ducky20">
    <AbsoluteLocation value="-2.357971 4.224264"/>
    <Properties>
      <Property name="Angle" value="0"/>
      <Property name="CutsRock" value="1"/>
      <Property name="Filename" value="/Objects/star_teleport.hs"/>
      <Property name="StarType" value="teleport"/>
      <Property name="TeleportMoveEase" value="both"/>
      <Property name="TeleportMoveTime" value="2"/>
      <Property name="TeleportWaitTime" value="2"/>
      <Property name="Type" value="star"/>
    </Properties>
  </Object>
  <Object name="Ducky13">
    <AbsoluteLocation value="-6.467346 -0.291361"/>
    <Properties>
      <Property name="Angle" value="0"/>
      <Property name="Filename" value="/Objects/star_teleport.hs"/>
      <Property name="StarType" value="teleport"/>
      <Property name="TeleportMoveEase" value="both"/>
      <Property name="TeleportMoveTime" value="2"/>
      <Property name="TeleportWaitTime" value="99999"/>
      <Property name="Type" value="star"/>
    </Properties>
  </Object>
  <Room>
    <AbsoluteLocation value="14.000002 -33.200005"/>
  </Room>
  <Properties>
    <Property name="HeavyIntro" value="1"/>
    <Property name="ShowTopEdge" value="1"/>
  </Properties>
</Objects>
